comments/__init__.py
comments/admin.py
comments/apps.py
comments/forms.py
comments/models.py
comments/signals.py
comments/urls.py
comments/utils.py
comments/views.py
comments/management/__init__.py
comments/management/commands/__init__.py
comments/management/commands/generate_test_comments.py
comments/migrations/0001_initial.py
comments/migrations/0002_comment_max_depth.py
comments/migrations/0003_auto_20170104_1329.py
comments/migrations/0004_auto_20171031_1357.py
comments/migrations/0005_comment_deleted.py
comments/migrations/0006_auto_20200331_1052.py
comments/migrations/0007_auto_20200423_0825.py
comments/migrations/0008_auto_20200708_1708.py
comments/migrations/0009_alter_comment_data.py
comments/migrations/__init__.py
comments/static/comments/css/comments.css
comments/static/comments/js/comments.js
comments/templates/comments/comment.html
comments/templates/comments/comments.html
comments/templates/comments/initialize.html
comments/templatetags/__init__.py
comments/templatetags/comments.py
django_nested_comments-2.0.5.dist-info/LICENSE
django_nested_comments-2.0.5.dist-info/METADATA
django_nested_comments-2.0.5.dist-info/WHEEL
django_nested_comments-2.0.5.dist-info/top_level.txt
django_nested_comments-2.0.5.dist-info/RECORD
