Metadata-Version: 2.1
Name: django-nested-comments
Version: 2.0.5
Summary: A Django application for handling comment uploads and associating them to arbitrary models.
Home-page: https://github.com/imsweb/django-nested-comments
Author: Noah Lefcourt
Author-email: lefcourn@imsweb.com
License: BSD
Platform: UNKNOWN
Classifier: Development Status :: 5 - Production/Stable
Classifier: Intended Audience :: Developers
Classifier: License :: OSI Approved :: BSD License
Classifier: Operating System :: OS Independent
Classifier: Programming Language :: Python :: 2
Classifier: Programming Language :: Python :: 3.2
Classifier: Programming Language :: Python :: 3.3
Classifier: Programming Language :: Python :: 3.4
Classifier: Programming Language :: Python :: 3.5
Classifier: Programming Language :: Python :: 3.6
Classifier: Topic :: Utilities
License-File: LICENSE
Requires-Dist: django-mptt (~=0.16.0)
Requires-Dist: nh3
